slack_emoji_attached/__init__.py
slack_emoji_attached/mod.py
garin54_slack_emoji_attached_strands-0.0.1.dist-info/WHEEL
garin54_slack_emoji_attached_strands-0.0.1.dist-info/entry_points.txt
garin54_slack_emoji_attached_strands-0.0.1.dist-info/METADATA
garin54_slack_emoji_attached_strands-0.0.1.dist-info/RECORD
