Metadata-Version: 2.3
Name: garin54-slack-emoji-attached-strands
Version: 0.0.1
Summary: Add your description here
Requires-Dist: strands-agents>=1.1.0
Requires-Dist: strands-agents-builder>=0.1.7
Requires-Dist: strands-agents-tools>=0.2.2
Requires-Python: >=3.13
